Workbook

Sheet Unit Economics
A1: Unit Economics: Grocery Chain Partnership
A2: Pre-Diabetic Family Weekly Food System | Fanny Polanco | BUS 395
A4: KEY ASSUMPTIONS
A5: Variable | B5: Value | C5: Type | D5: Comments
A6: Revenue per active user / month | B6: 5 | C6: ASSUMPTION | D6: Below PlateJoy $30-50/member healthcare rate (no HIPAA); above $1-2 loyalty punch-card tech. No chain approached yet.
A7: AI inference / user / month | B7: 0.35 | C7: DATA | D7: Calculated from published Claude API pricing. ~6,900 input + 2,500 output tokens/plan x4 plans + mid-week interactions + 20% buffer.
A8: Hosting variable / user / month | B8: 0.1 | C8: ASSUMPTION | D8: Compute + storage beyond base, security-grade tier for health-adjacent data.
A9: Customer support / user / month | B9: 0.15 | C9: ASSUMPTION | D9: ~3% monthly contact rate at 15 min each.
A10: Hosting base / month (fixed) | B10: 200 | C10: ASSUMPTION | D10: Security-grade cloud tier (encrypted storage, access controls, audit logging).
A11: Data integration maint / month (fixed) | B11: 400 | C11: ASSUMPTION | D11: Weekly circular ingestion pipeline: parsing, price normalization, SKU matching. 4-6 hrs/mo.
A12: Clinical advisor / month (fixed) | B12: 3000 | C12: ASSUMPTION | D12: RD/CDE, 20 hrs/mo at $150/hr. Spot-checks, logic review on model/guideline updates, flagged reports.
A13: Insurance / month (fixed) | B13: 600 | C13: ASSUMPTION | D13: E&O + product liability + cyber/data-breach + general. Health-adjacent product.
A14: Compliance tooling / month (fixed) | B14: 200 | C14: ASSUMPTION | D14: CCPA obligations; privacy policy + consent management tooling.
A15: QA automation / month (fixed) | B15: 100 | C15: ASSUMPTION | D15: Automated budget/flagged-food/glycemic checks as backstop to spot review.
A16: Founder hourly rate | B16: 0 | C16: PER ASSIGNMENT | D16: Valued at $0 per assignment instruction. Real hours ~22-34/mo (tracked, not valued).
A17: Active users (for fixed-cost allocation) | B17: 500 | C17: ASSUMPTION | D17: Reference cohort size for per-user allocation of base infrastructure.
A19: CALCULATED VALUES
A20: Metric | B20: Value | C20: Formula | D20: Comments
A21: COGS per user (incl. allocated infra) | B21: =(B7+B8+B9+(B10+B11)/B17) -> 1.8 | C21: AI + hosting var + support + (hosting base + data integ)/users | D21: All per-user variable costs.
A22: Gross margin per user / month | B22: =B6-(B7+B8+B9+(B10+B11)/B17) -> 3.2 | C22: Revenue - COGS per user | D22: Contribution per active user before fixed costs.
A23: Gross margin % | B23: =(B6-(B7+B8+B9+(B10+B11)/B17))/B6 -> 0.64 | C23: Margin / revenue | D23: Target realistic range 60-70% for health-adjacent AI SaaS.
A24: Total operating expenses / month | B24: =B12+B13+B14+B15 -> 3900 | C24: Clinical + insurance + compliance + QA (not in COGS) | D24: Operating cost stack once live at scale.
A25: Break-even active users | B25: =(B12+B13+B14+B15)/(B6-(B7+B8+B9+(B10+B11)/B17)) -> 1218.75 | C25: Operating expenses / gross margin per user | D25: Users needed from one chain deal to cover fixed costs.

Sheet Financial Model
A1: Financial Model: First 6 Months
A2: Three scenarios differ by ASSUMPTIONS (deal-close timing, chain promotion, churn) - not just volume.
A4: PESSIMISTIC SCENARIO
A5: Cold outreach, no champion; chain treats tool as a background feature. Deal closes Month 6; 40%/mo churn (matches interview abandonment pattern).
A6: Month | B6: M1 | C6: M2 | D6: M3 | E6: M4 | F6: M5 | G6: M6 | H6: Assumptions
A7: Active users | B7: 0 | C7: 0 | D7: 0 | E7: 0 | F7: 0 | G7: 250 | H7: Deal closes M6 at 0.5% activation of 50k base. No active promotion. 40% churn = interview-pattern.
A8: Revenue | B8: =B7*'Unit Economics'!B6 -> 0 | C8: =C7*'Unit Economics'!B6 -> 0 | D8: =D7*'Unit Economics'!B6 -> 0 | E8: =E7*'Unit Economics'!B6 -> 0 | F8: =F7*'Unit Economics'!B6 -> 0 | G8: =G7*'Unit Economics'!B6 -> 1250 | H8: Active users x rate ('Unit Economics'!B6).
A9: Variable costs | B9: =B7*'Unit Economics'!B22*0+B7*('Unit Economics'!B7+'Unit Economics'!B8+'Unit Economics'!B9) -> 0 | C9: =C7*'Unit Economics'!B22*0+C7*('Unit Economics'!B7+'Unit Economics'!B8+'Unit Economics'!B9) -> 0 | D9: =D7*'Unit Economics'!B22*0+D7*('Unit Economics'!B7+'Unit Economics'!B8+'Unit Economics'!B9) -> 0 | E9: =E7*'Unit Economics'!B22*0+E7*('Unit Economics'!B7+'Unit Economics'!B8+'Unit Economics'!B9) -> 0 | F9: =F7*'Unit Economics'!B22*0+F7*('Unit Economics'!B7+'Unit Economics'!B8+'Unit Economics'!B9) -> 0 | G9: =G7*'Unit Economics'!B22*0+G7*('Unit Economics'!B7+'Unit Economics'!B8+'Unit Economics'!B9) -> 150 | H9: Active users x variable cost/user.
A10: Fixed costs | B10: ='Unit Economics'!B24 -> 3900 | C10: ='Unit Economics'!B24 -> 3900 | D10: ='Unit Economics'!B24 -> 3900 | E10: ='Unit Economics'!B24 -> 3900 | F10: ='Unit Economics'!B24 -> 3900 | G10: ='Unit Economics'!B24 -> 3900 | H10: Full operating stack from Unit Economics (live-scale assumption).
A11: Net | B11: =B8-B9-B10 -> -3900 | C11: =C8-C9-C10 -> -3900 | D11: =D8-D9-D10 -> -3900 | E11: =E8-E9-E10 -> -3900 | F11: =F8-F9-F10 -> -3900 | G11: =G8-G9-G10 -> -2800
A12: Cumulative net | B12: =B11 -> -3900 | C12: =B12+C11 -> -7800 | D12: =C12+D11 -> -11700 | E12: =D12+E11 -> -15600 | F12: =E12+F11 -> -19500 | G12: =F12+G11 -> -22300
A14: BASE SCENARIO
A15: Deal closes mid-window with modest promotion; 0.5% activation; 20% monthly churn (assumes grocery context softens abandonment - unproven).
A16: Month | B16: M1 | C16: M2 | D16: M3 | E16: M4 | F16: M5 | G16: M6 | H16: Assumptions
A17: Active users | B17: 0 | C17: 0 | D17: 250 | E17: =ROUND(D17*(1-0.2),0) -> 200 | F17: =ROUND(E17*(1-0.2),0) -> 160 | G17: =ROUND(F17*(1-0.2),0) -> 128 | H17: Deal closes M3, 250 users. 20% churn is a hope pending Wizard-of-Oz evidence.
A18: Revenue | B18: =B17*'Unit Economics'!B6 -> 0 | C18: =C17*'Unit Economics'!B6 -> 0 | D18: =D17*'Unit Economics'!B6 -> 1250 | E18: =E17*'Unit Economics'!B6 -> 1000 | F18: =F17*'Unit Economics'!B6 -> 800 | G18: =G17*'Unit Economics'!B6 -> 640 | H18: Active users x rate ('Unit Economics'!B6).
A19: Variable costs | B19: =B17*'Unit Economics'!B22*0+B17*('Unit Economics'!B7+'Unit Economics'!B8+'Unit Economics'!B9) -> 0 | C19: =C17*'Unit Economics'!B22*0+C17*('Unit Economics'!B7+'Unit Economics'!B8+'Unit Economics'!B9) -> 0 | D19: =D17*'Unit Economics'!B22*0+D17*('Unit Economics'!B7+'Unit Economics'!B8+'Unit Economics'!B9) -> 150 | E19: =E17*'Unit Economics'!B22*0+E17*('Unit Economics'!B7+'Unit Economics'!B8+'Unit Economics'!B9) -> 120 | F19: =F17*'Unit Economics'!B22*0+F17*('Unit Economics'!B7+'Unit Economics'!B8+'Unit Economics'!B9) -> 96 | G19: =G17*'Unit Economics'!B22*0+G17*('Unit Economics'!B7+'Unit Economics'!B8+'Unit Economics'!B9) -> 76.8 | H19: Active users x variable cost/user.
A20: Fixed costs | B20: ='Unit Economics'!B24 -> 3900 | C20: ='Unit Economics'!B24 -> 3900 | D20: ='Unit Economics'!B24 -> 3900 | E20: ='Unit Economics'!B24 -> 3900 | F20: ='Unit Economics'!B24 -> 3900 | G20: ='Unit Economics'!B24 -> 3900 | H20: Full operating stack from Unit Economics (live-scale assumption).
A21: Net | B21: =B18-B19-B20 -> -3900 | C21: =C18-C19-C20 -> -3900 | D21: =D18-D19-D20 -> -2800 | E21: =E18-E19-E20 -> -3020 | F21: =F18-F19-F20 -> -3196 | G21: =G18-G19-G20 -> -3336.8
A22: Cumulative net | B22: =B21 -> -3900 | C22: =B22+C21 -> -7800 | D22: =C22+D21 -> -10600 | E22: =D22+E21 -> -13620 | F22: =E22+F21 -> -16816 | G22: =F22+G21 -> -20152.8
A24: OPTIMISTIC SCENARIO
A25: Warm intro; chain actively promotes the tool; ~2% activation; 10% monthly churn.
A26: Month | B26: M1 | C26: M2 | D26: M3 | E26: M4 | F26: M5 | G26: M6 | H26: Assumptions
A27: Active users | B27: 0 | C27: 1000 | D27: =ROUND(C27*(1-0.1),0) -> 900 | E27: =ROUND(D27*(1-0.1),0) -> 810 | F27: =ROUND(E27*(1-0.1),0) -> 729 | G27: =ROUND(F27*(1-0.1),0) -> 656 | H27: Deal closes M2, 1,000 users (2% of 50k). Active promotion; 10% churn.
A28: Revenue | B28: =B27*'Unit Economics'!B6 -> 0 | C28: =C27*'Unit Economics'!B6 -> 5000 | D28: =D27*'Unit Economics'!B6 -> 4500 | E28: =E27*'Unit Economics'!B6 -> 4050 | F28: =F27*'Unit Economics'!B6 -> 3645 | G28: =G27*'Unit Economics'!B6 -> 3280 | H28: Active users x rate ('Unit Economics'!B6).
A29: Variable costs | B29: =B27*'Unit Economics'!B22*0+B27*('Unit Economics'!B7+'Unit Economics'!B8+'Unit Economics'!B9) -> 0 | C29: =C27*'Unit Economics'!B22*0+C27*('Unit Economics'!B7+'Unit Economics'!B8+'Unit Economics'!B9) -> 600 | D29: =D27*'Unit Economics'!B22*0+D27*('Unit Economics'!B7+'Unit Economics'!B8+'Unit Economics'!B9) -> 540 | E29: =E27*'Unit Economics'!B22*0+E27*('Unit Economics'!B7+'Unit Economics'!B8+'Unit Economics'!B9) -> 486 | F29: =F27*'Unit Economics'!B22*0+F27*('Unit Economics'!B7+'Unit Economics'!B8+'Unit Economics'!B9) -> 437.4 | G29: =G27*'Unit Economics'!B22*0+G27*('Unit Economics'!B7+'Unit Economics'!B8+'Unit Economics'!B9) -> 393.6 | H29: Active users x variable cost/user.
A30: Fixed costs | B30: ='Unit Economics'!B24 -> 3900 | C30: ='Unit Economics'!B24 -> 3900 | D30: ='Unit Economics'!B24 -> 3900 | E30: ='Unit Economics'!B24 -> 3900 | F30: ='Unit Economics'!B24 -> 3900 | G30: ='Unit Economics'!B24 -> 3900 | H30: Full operating stack from Unit Economics (live-scale assumption).
A31: Net | B31: =B28-B29-B30 -> -3900 | C31: =C28-C29-C30 -> 500 | D31: =D28-D29-D30 -> 60 | E31: =E28-E29-E30 -> -336 | F31: =F28-F29-F30 -> -692.4 | G31: =G28-G29-G30 -> -1013.6
A32: Cumulative net | B32: =B31 -> -3900 | C32: =B32+C31 -> -3400 | D32: =C32+D31 -> -3340 | E32: =D32+E31 -> -3676 | F32: =E32+F31 -> -4368.4 | G32: =F32+G31 -> -5382
A34: KEY TAKEAWAYS
A35: 1. | B35: No scenario breaks even in 6 months. Base ends deeply negative and is still climbing toward break-even.
A36: 2. | B36: Short-term swing variable = WHEN the deal closes. Each pre-revenue month costs the full fixed stack (~$4,500) with $0 revenue.
A37: 3. | B37: Long-term swing variable = the chain RATE. $2 vs $5 is a binary viability gate (break-even ~3,214 users at $2 - not achievable from one regional pilot).
A38: 4. | B38: To break even: defer the full fixed stack until near-deal (pre-launch real cost ~$500-800/mo), secure active chain promotion (push activation toward 2%), and solve churn.
A39: 5. | B39: Biggest risk = churn. Interview data supports 40%, not the 20% base assumption. At 40%, a 250-user base decays to ~11 within six months.

Sheet Sensitivity
A1: Sensitivity Analysis
A2: Change one variable at a time. Break-even users = fixed costs / gross margin per user.
A4: CHAIN RATE PER USER / MONTH
A5: Rate/user | B5: Gross margin/user | C5: Gross margin % | D5: Break-even users | F5: Comments
A6: 2 | B6: =A6-('Unit Economics'!B7+'Unit Economics'!B8+'Unit Economics'!B9+('Unit Economics'!B10+'Unit Economics'!B11)/'Unit Economics'!B17) -> 0.2 | C6: =(A6-('Unit Economics'!B7+'Unit Economics'!B8+'Unit Economics'!B9+('Unit Economics'!B10+'Unit Economics'!B11)/'Unit Economics'!B17))/A6 -> 0.1 | D6: =('Unit Economics'!B12+'Unit Economics'!B13+'Unit Economics'!B14+'Unit Economics'!B15)/(A6-('Unit Economics'!B7+'Unit Economics'!B8+'Unit Economics'!B9+('Unit Economics'!B10+'Unit Economics'!B11)/'Unit Economics'!B17)) -> 19500 | F6: Background loyalty feature. Margin collapses; not viable.
A7: 3 | B7: =A7-('Unit Economics'!B7+'Unit Economics'!B8+'Unit Economics'!B9+('Unit Economics'!B10+'Unit Economics'!B11)/'Unit Economics'!B17) -> 1.2 | C7: =(A7-('Unit Economics'!B7+'Unit Economics'!B8+'Unit Economics'!B9+('Unit Economics'!B10+'Unit Economics'!B11)/'Unit Economics'!B17))/A7 -> 0.4 | D7: =('Unit Economics'!B12+'Unit Economics'!B13+'Unit Economics'!B14+'Unit Economics'!B15)/(A7-('Unit Economics'!B7+'Unit Economics'!B8+'Unit Economics'!B9+('Unit Economics'!B10+'Unit Economics'!B11)/'Unit Economics'!B17)) -> 3250 | F7: Still thin. Break-even out of reach for one pilot.
A8: 5 | B8: =A8-('Unit Economics'!B7+'Unit Economics'!B8+'Unit Economics'!B9+('Unit Economics'!B10+'Unit Economics'!B11)/'Unit Economics'!B17) -> 3.2 | C8: =(A8-('Unit Economics'!B7+'Unit Economics'!B8+'Unit Economics'!B9+('Unit Economics'!B10+'Unit Economics'!B11)/'Unit Economics'!B17))/A8 -> 0.64 | D8: =('Unit Economics'!B12+'Unit Economics'!B13+'Unit Economics'!B14+'Unit Economics'!B15)/(A8-('Unit Economics'!B7+'Unit Economics'!B8+'Unit Economics'!B9+('Unit Economics'!B10+'Unit Economics'!B11)/'Unit Economics'!B17)) -> 1218.75 | F8: Base assumption. Hard but real (~1,200 users).
A9: 7 | B9: =A9-('Unit Economics'!B7+'Unit Economics'!B8+'Unit Economics'!B9+('Unit Economics'!B10+'Unit Economics'!B11)/'Unit Economics'!B17) -> 5.2 | C9: =(A9-('Unit Economics'!B7+'Unit Economics'!B8+'Unit Economics'!B9+('Unit Economics'!B10+'Unit Economics'!B11)/'Unit Economics'!B17))/A9 -> 0.74285714 | D9: =('Unit Economics'!B12+'Unit Economics'!B13+'Unit Economics'!B14+'Unit Economics'!B15)/(A9-('Unit Economics'!B7+'Unit Economics'!B8+'Unit Economics'!B9+('Unit Economics'!B10+'Unit Economics'!B11)/'Unit Economics'!B17)) -> 750 | F9: Positioned as wellness benefit. Achievable.
A10: 10 | B10: =A10-('Unit Economics'!B7+'Unit Economics'!B8+'Unit Economics'!B9+('Unit Economics'!B10+'Unit Economics'!B11)/'Unit Economics'!B17) -> 8.2 | C10: =(A10-('Unit Economics'!B7+'Unit Economics'!B8+'Unit Economics'!B9+('Unit Economics'!B10+'Unit Economics'!B11)/'Unit Economics'!B17))/A10 -> 0.82 | D10: =('Unit Economics'!B12+'Unit Economics'!B13+'Unit Economics'!B14+'Unit Economics'!B15)/(A10-('Unit Economics'!B7+'Unit Economics'!B8+'Unit Economics'!B9+('Unit Economics'!B10+'Unit Economics'!B11)/'Unit Economics'!B17)) -> 475.60976 | F10: Diabetes-prevention benefit framing - reintroduces clinical/compliance burden.
A13: MONTHLY CHURN (users retained from 250 after 6 months)
A14: Churn/mo | B14: After 3 mo | C14: After 6 mo | F14: Comments
A15: 0.1 | B15: =ROUND(250*(1-A15)^3,0) -> 182 | C15: =ROUND(250*(1-A15)^6,0) -> 133 | F15: Optimistic. Grocery context strongly changes behavior.
A16: 0.2 | B16: =ROUND(250*(1-A16)^3,0) -> 128 | C16: =ROUND(250*(1-A16)^6,0) -> 66 | F16: Base assumption (unproven hope).
A17: 0.3 | B17: =ROUND(250*(1-A17)^3,0) -> 86 | C17: =ROUND(250*(1-A17)^6,0) -> 29 | F17: Midpoint.
A18: 0.4 | B18: =ROUND(250*(1-A18)^3,0) -> 54 | C18: =ROUND(250*(1-A18)^6,0) -> 12 | F18: What the interview data actually supports.

Sheet Cost Audit
A1: Cost Audit Trail: How the Numbers Changed
A2: AI undercounted costs and produced a 95% margin. Pushback corrected three costs and added five missing ones.
A4: Cost Category | B4: AI First Pass | C4: After Pushback | D4: Type | E4: Comments
A5: AI inference / user | B5: 0.17 | C5: 0.35 | D5: DATA | E5: Token count was 3x too low. Real plan needs circular (~3k tokens), rules, profile, pantry, prior week + mid-week interactions.
A6: Hosting variable / user | B6: 0.1 | C6: 0.1 | D6: ASSUMPTION | E6: Unchanged per-user; base tier upgraded to security-grade (see fixed).
A7: Customer support / user | B7: 0 | C7: 0.15 | D7: ASSUMPTION | E7: Was $0. ~3% monthly contact rate is real even for a pull-based product.
A8: Hosting base / month | B8: 100 | C8: 200 | D8: ASSUMPTION | E8: Health-adjacent data needs encrypted storage, access controls, audit logging.
A9: Data integration / month | B9: 0 | C9: 400 | D9: ASSUMPTION | E9: Was $0 ("chain supplies data"). Circular is a PDF/flat file - building+maintaining the pipeline is real work.
A10: Clinical advisor / month | B10: 1000 | C10: 3000 | D10: ASSUMPTION | E10: Was scoped for launch. 8 hrs reviews <1.5% of plans at scale. 20 hrs/mo minimum for an evolving health product.
A11: Insurance / month | B11: 150 | C11: 600 | D11: ASSUMPTION | E11: Was general-business. Needs E&O + product liability + cyber/data-breach for medical-adjacent recommendations.
A12: Compliance tooling / month | B12: 0 | C12: 200 | D12: ASSUMPTION | E12: Was $0. CCPA applies to health-adjacent personal data.
A13: QA automation / month | B13: 0 | C13: 100 | D13: ASSUMPTION | E13: Was $0. Automated checks back up the <2% human spot-review.
A15: RESULTING GROSS MARGIN
A16: Gross margin per user (at $5 rate) | B16: =5-0.17-0.1-(100)/500 -> 4.53 | C16: =5-0.35-0.1-0.15-(200+400)/500 -> 3.2 | E16: Per-user contribution before fixed costs.
A17: Gross margin % | B17: =(5-0.17-0.1-(100)/500)/5 -> 0.906 | C17: =(5-0.35-0.1-0.15-(200+400)/500)/5 -> 0.64 | E17: From 95% fantasy to 64% realistic (health-adjacent AI SaaS range 60-70%).
A19: LESSONS FROM THE AUDIT
A20: 1. | B20: AI zeroed out every uncertain cost (data integration, support, compliance, QA all came back $0).
A21: 2. | B21: The 95% margin was the tell. Any margin above 80% means costs are missing - that was the cue to push back.
A22: 3. | B22: Founder time is the hidden cost: tracked at 22-34 hrs/mo but valued at $0 per assignment. At market rate this is $1,100-2,550/mo.
A23: 4. | B23: The load-bearing number is the chain rate. At $2/user the model loses money on every user before fixed costs even apply.
